README.md
sqlapydantic/__init__.py
sqlapydantic/generator.py
sqlapydantic/models.py
sqlapydantic/utils.py
sqlapydantic-0.0.4.dist-info/LICENSE
sqlapydantic-0.0.4.dist-info/METADATA
sqlapydantic-0.0.4.dist-info/WHEEL
sqlapydantic-0.0.4.dist-info/RECORD
