Metadata-Version: 2.1
Name: sqlapydantic
Version: 0.0.4
Summary: Generate pydantic models from SQLAlchemy models
Home-page: https://github.com/maacck/sqlapydantic
Keywords: pydantic,sqlalchemy
Author: maacck
Author-email: c.mai@madainchina.com
Requires-Python: >=3.8,<4.0
Classifier: Programming Language :: Python :: 3
Classifier: Programming Language :: Python :: 3.8
Classifier: Programming Language :: Python :: 3.9
Classifier: Programming Language :: Python :: 3.10
Classifier: Programming Language :: Python :: 3.11
Requires-Dist: SQLAlchemy (>=2.0.13,<3.0.0)
Requires-Dist: pydantic (>=2.0.2,<3.0.0)
Project-URL: BUG TRACKER, https://github.com/maacck/sqlapydantic/issues
Project-URL: Repository, https://github.com/maacck/sqlapydantic
